twitch_mcp/__init__.py
twitch_mcp/eventsub/__init__.py
twitch_mcp/eventsub/handlers.py
twitch_mcp/eventsub/listener.py
twitch_mcp/server.py
twitch_mcp/setup.py
twitch_mcp/tools/__init__.py
twitch_mcp/tools/ads.py
twitch_mcp/tools/analytics.py
twitch_mcp/tools/bits.py
twitch_mcp/tools/channel_points.py
twitch_mcp/tools/channels.py
twitch_mcp/tools/charity.py
twitch_mcp/tools/chat.py
twitch_mcp/tools/clips.py
twitch_mcp/tools/eventsub.py
twitch_mcp/tools/games.py
twitch_mcp/tools/goals.py
twitch_mcp/tools/guest_star.py
twitch_mcp/tools/moderation.py
twitch_mcp/tools/polls.py
twitch_mcp/tools/predictions.py
twitch_mcp/tools/raids.py
twitch_mcp/tools/schedule.py
twitch_mcp/tools/search.py
twitch_mcp/tools/streams.py
twitch_mcp/tools/subscriptions.py
twitch_mcp/tools/teams.py
twitch_mcp/tools/users.py
twitch_mcp/tools/videos.py
twitch_mcp/tools/whispers.py
twitch_mcp-0.2.0.dist-info/METADATA
twitch_mcp-0.2.0.dist-info/WHEEL
twitch_mcp-0.2.0.dist-info/entry_points.txt
twitch_mcp-0.2.0.dist-info/licenses/LICENSE
twitch_mcp-0.2.0.dist-info/RECORD
