Metadata-Version: 2.4
Name: twitch-mcp
Version: 0.2.0
Summary: MCP server exposing Twitch SDK as tools for AI assistants
License-Expression: MIT
License-File: LICENSE
Keywords: twitch,mcp,ai,claude,tools,streaming,api
Author: ldraney
Requires-Python: >=3.10,<4.0
Classifier: Development Status :: 4 - Beta
Classifier: Intended Audience :: Developers
Classifier: Operating System :: OS Independent
Classifier: Programming Language :: Python :: 3
Classifier: Programming Language :: Python :: 3.10
Classifier: Programming Language :: Python :: 3.11
Classifier: Programming Language :: Python :: 3.12
Classifier: Programming Language :: Python :: 3.13
Classifier: Topic :: Software Development :: Libraries :: Python Modules
Classifier: Topic :: Communications :: Chat
Classifier: Framework :: AsyncIO
Requires-Dist: mcp (>=1.0.0,<2.0.0)
Requires-Dist: twitch-sdk (>=0.1.2,<0.2.0)
Project-URL: Documentation, https://github.com/ldraney/twitch-mcp#readme
Project-URL: Homepage, https://github.com/ldraney/twitch-mcp
Project-URL: Issues, https://github.com/ldraney/twitch-mcp/issues
Project-URL: Repository, https://github.com/ldraney/twitch-mcp
